biobss/__init__.py
biobss/common/__init__.py
biobss/common/signal_entropy.py
biobss/common/signal_fft.py
biobss/common/signal_hjorth.py
biobss/common/signal_psd.py
biobss/ecgtools/__init__.py
biobss/ecgtools/ecg_features.py
biobss/ecgtools/ecg_filter.py
biobss/ecgtools/ecg_peaks.py
biobss/ecgtools/ecg_plot.py
biobss/ecgtools/ecg_sqa.py
biobss/edatools/__init__.py
biobss/edatools/eda_decompose.py
biobss/edatools/eda_features.py
biobss/edatools/eda_filter.py
biobss/edatools/eda_freqdomain.py
biobss/edatools/eda_hjorth.py
biobss/edatools/eda_peaks.py
biobss/edatools/eda_plot.py
biobss/edatools/eda_signalfeatures.py
biobss/edatools/eda_statistical.py
biobss/hrvtools/__init__.py
biobss/hrvtools/hrv_features.py
biobss/hrvtools/hrv_freqdomain.py
biobss/hrvtools/hrv_nonlinear.py
biobss/hrvtools/hrv_timedomain.py
biobss/imutools/__init__.py
biobss/imutools/acc_activityindex.py
biobss/imutools/acc_correlation.py
biobss/imutools/acc_features.py
biobss/imutools/acc_filter.py
biobss/imutools/acc_freqdomain.py
biobss/imutools/acc_plot.py
biobss/imutools/acc_statistical.py
biobss/pipeline/__init__.py
biobss/pipeline/bio_channel.py
biobss/pipeline/bio_data.py
biobss/pipeline/bio_process.py
biobss/pipeline/bioprocess_queue.py
biobss/pipeline/channel_input.py
biobss/pipeline/event_channel.py
biobss/pipeline/event_input.py
biobss/pipeline/feature_extraction.py
biobss/pipeline/feature_queue.py
biobss/pipeline/pipeline.py
biobss/pipeline/pipeline_export.py
biobss/plottools/__init__.py
biobss/plottools/plot_tools.py
biobss/ppgtools/__init__.py
biobss/ppgtools/apg_features.py
biobss/ppgtools/ppg_features.py
biobss/ppgtools/ppg_filter.py
biobss/ppgtools/ppg_freqdomain.py
biobss/ppgtools/ppg_peaks.py
biobss/ppgtools/ppg_plot.py
biobss/ppgtools/ppg_sqa.py
biobss/ppgtools/ppg_statistical.py
biobss/ppgtools/ppg_timedomain.py
biobss/ppgtools/vpg_features.py
biobss/preprocess/__init__.py
biobss/preprocess/signal_detectpeaks.py
biobss/preprocess/signal_filter.py
biobss-0.1.1.dist-info/LICENSE
biobss-0.1.1.dist-info/METADATA
biobss-0.1.1.dist-info/WHEEL
biobss-0.1.1.dist-info/top_level.txt
biobss-0.1.1.dist-info/RECORD
