Metadata-Version: 2.1
Name: biobss
Version: 0.1.1
Summary: A biological signal processing and feature extraction library.
Home-page: https://github.com/obss/BIOBSS
Author: OBSS R&D
License: MIT
Keywords: signal processing,feature extraction,photoplethysmography,PPG,electrocardiography,ECG,acceleration,electrodermal activity,EDA,galvanic skin response,HRV,Heart Rate Variability
Classifier: Development Status :: 5 - Production/Stable
Classifier: Operating System :: OS Independent
Classifier: Intended Audience :: Developers
Classifier: Intended Audience :: Science/Research
Classifier: Programming Language :: Python :: 3.8
Classifier: Programming Language :: Python :: 3.9
Classifier: Topic :: Software Development :: Libraries
Classifier: Topic :: Software Development :: Libraries :: Python Modules
Classifier: Topic :: Education
Classifier: Topic :: Scientific/Engineering
Requires-Python: >=3.8
Provides-Extra: dev
License-File: LICENSE
